gpfetcher/__init__.py
gpfetcher/scraper.py
gpfetcher-0.8.6.dist-info/LICENSE
gpfetcher-0.8.6.dist-info/METADATA
gpfetcher-0.8.6.dist-info/WHEEL
gpfetcher-0.8.6.dist-info/top_level.txt
gpfetcher-0.8.6.dist-info/RECORD
