Metadata-Version: 2.1
Name: gpfetcher
Version: 0.8.6
Summary: A python package that fetches your public project(repos) details from github
Home-page: UNKNOWN
Author: Gautam Chandra Saha
Author-email: devgautam1231@gmail.com
License: UNKNOWN
Keywords: python,github,projects,repositories,JSON,scraper
Platform: UNKNOWN
Classifier: Development Status :: 1 - Planning
Classifier: Intended Audience :: Developers
Classifier: Programming Language :: Python :: 3
Classifier: Operating System :: Unix
Classifier: Operating System :: MacOS :: MacOS X
Classifier: Operating System :: Microsoft :: Windows
License-File: LICENSE
Requires-Dist: bs4
Requires-Dist: requests
Requires-Dist: tqdm
Requires-Dist: lxml
